dfsspy/__init__.py
dfsspy/__main__.py
dfsspy/util.py
dfss_py-1.6.20.dist-info/METADATA
dfss_py-1.6.20.dist-info/WHEEL
dfss_py-1.6.20.dist-info/top_level.txt
dfss_py-1.6.20.dist-info/RECORD
